Workbook

Sheet README
A1: L3 Schedule (Synthetic Case)
A3: Purpose | B3: The consultant-level (L3) schedule for the case project, from investment approval to commissioning. It shows where the construction contractor's L4-L6 schedule sits in the whole project and gives the students the parent activities to which field updates roll up.
A4: Sheets | B4: L3 Schedule: activities, logic, dates and a monthly bar chart. Key Dates: milestones and consistency checks. This README.
A5: Phases | B5: 1 Project Initiation, Approval & Land; 2 Statutory Clearances & Inspections; 3 Utility Arrangements; 4 Design & Engineering; 5 Procurement; 6 Equipment Manufacture, Inspection & Delivery; 7 Construction (Contractor Package); 8 Completion, Pre-commissioning & Commissioning.
A6: Activity IDs | B6: Format GWP-L3-nnn. The 11 contractor L3 activities are GWP-L3-010 to GWP-L3-110 and match the L4-L6 Schedule workbook. Other packages use the hundreds digit: 2xx approval and land, 3xx statutory, 4xx utilities, 5xx design, 6xx procurement, 8xx supplier manufacture and delivery, 9xx completion and commissioning. Phase rows are GWP-PH-n.
A7: Link to L4-L6 workbook | B7: Contractor rows (green bars) carry fixed start and finish dates copied from the L4-L6 Schedule workbook. Site handover (GWP-L3-000) is driven by contract award and statutory logic and lands on the handover date that workbook assumes. The Key Dates sheet checks this.
A8: Back-solved durations | B8: Durations of GWP-L3-530, 640 and the equipment manufacture rows (810 to 860) were set so that structural steel IFC release, contract signing and supplier deliveries land on the dates assumed in the L4-L6 workbook. They are illustrative.
A9: Logic and calendar | B9: Finish-to-Start unless stated, with a few Start-to-Start lags. Six-day week (Sunday off), no holidays. Total float is not calculated. Durations and logic are synthetic assumptions for teaching, not from any real project.
A10: Legend | B10: Blue text: hardcoded input. Black: formula. Green text: link to another sheet. Yellow fill: key input to change. Bar colours: navy = phase, blue = L3 activity, green = contractor fixed window, red = milestone.
A11: Result | B11: Approval on 1 Jan 2027; site handover 4 Oct 2027; Mechanical Completion 20 Jul 2028; commissioning acceptance 22 Dec 2028, about one week before the 31 Dec 2028 target. See Key Dates.

Sheet L3 Schedule
A1: Level 3 Schedule: Urban Garbage Treatment Plant (100 TPD), Town XYZ, Company ABC - Investment Approval to Commissioning
A2: Synthetic teaching schedule in Primavera P6 style. Blue = input, black = formula. Contractor L3 windows (green) are fixed from the L4-L6 Schedule workbook. Six-day week (Sunday off).
A5: Activity ID | B5: WBS | C5: Level | D5: Activity Name | E5: Type | F5: Responsible | G5: Orig Duration (wd) | H5: Predecessors (FS unless stated) | I5: Planned Start | J5: Planned Finish | K5: 46388 | L5: =EDATE(K5,1) -> 46419 | M5: =EDATE(L5,1) -> 46447 | N5: =EDATE(M5,1) -> 46478 | O5: =EDATE(N5,1) -> 46508 | P5: =EDATE(O5,1) -> 46539 | Q5: =EDATE(P5,1) -> 46569 | R5: =EDATE(Q5,1) -> 46600 | S5: =EDATE(R5,1) -> 46631 | ... AH5: =EDATE(AG5,1) -> 47088
A6: GWP-PH-1 | B6: GWP.01 | C6: Phase | D6: Project Initiation, Approval & Land Acquisition | G6: =NETWORKDAYS.INTL(I6,J6,11) -> 106 | I6: =MIN(I7:I16) -> 46388 | J6: =MAX(J7:J16) -> 46511
A7: GWP-L3-200 | B7: GWP.01.01 | C7: L3 | D7: Investment approval by Company ABC Board | E7: Milestone | F7: Company ABC | G7: 0 | H7: Board decision date (input) | I7: 46388 | J7: =I7 -> 46388
A8: GWP-L3-210 | B8: GWP.01.02 | C8: L3 | D8: Appoint project management consultant (PMC) | E8: Task | F8: Company ABC | G8: 40 | H8: GWP-L3-200 FS | I8: =IF($G8=0,J7,WORKDAY.INTL(J7,1,11)) -> 46389 | J8: =IF(G8=0,I8,WORKDAY.INTL(I8,G8-1,11)) -> 46435
A9: GWP-L3-220 | B9: GWP.01.03 | C9: L3 | D9: Project organisation, budget & baseline schedule approval | E9: Task | F9: Company ABC | G9: 20 | H9: GWP-L3-210 FS | I9: =IF($G9=0,J8,WORKDAY.INTL(J8,1,11)) -> 46436 | J9: =IF(G9=0,I9,WORKDAY.INTL(I9,G9-1,11)) -> 46458
A10: GWP-L3-230 | B10: GWP.01.04 | C10: L3 | D10: Identify and finalise land parcel | E10: Task | F10: Company ABC | G10: 20 | H10: GWP-L3-200 FS | I10: =IF($G10=0,J7,WORKDAY.INTL(J7,1,11)) -> 46389 | J10: =IF(G10=0,I10,WORKDAY.INTL(I10,G10-1,11)) -> 46412
A11: GWP-L3-240 | B11: GWP.01.05 | C11: L3 | D11: Land title verification & due diligence | E11: Task | F11: Company ABC | G11: 15 | H11: GWP-L3-230 FS | I11: =IF($G11=0,J10,WORKDAY.INTL(J10,1,11)) -> 46413 | J11: =IF(G11=0,I11,WORKDAY.INTL(I11,G11-1,11)) -> 46429
A12: GWP-L3-250 | B12: GWP.01.06 | C12: L3 | D12: Land transfer / lease agreement with municipality | E12: Task | F12: Company ABC | G12: 25 | H12: GWP-L3-240 FS | I12: =IF($G12=0,J11,WORKDAY.INTL(J11,1,11)) -> 46430 | J12: =IF(G12=0,I12,WORKDAY.INTL(I12,G12-1,11)) -> 46458
A13: GWP-L3-260 | B13: GWP.01.07 | C13: L3 | D13: Land registration & mutation | E13: Task | F13: Company ABC | G13: 15 | H13: GWP-L3-250 FS | I13: =IF($G13=0,J12,WORKDAY.INTL(J12,1,11)) -> 46459 | J13: =IF(G13=0,I13,WORKDAY.INTL(I13,G13-1,11)) -> 46476
A14: GWP-L3-270 | B14: GWP.01.08 | C14: L3 | D14: Land possession & boundary demarcation | E14: Task | F14: Company ABC | G14: 5 | H14: GWP-L3-260 FS | I14: =IF($G14=0,J13,WORKDAY.INTL(J13,1,11)) -> 46477 | J14: =IF(G14=0,I14,WORKDAY.INTL(I14,G14-1,11)) -> 46482
A15: GWP-L3-275 | B15: GWP.01.09 | C15: L3 | D15: Topographic survey | E15: Task | F15: PMC / Consultant | G15: 10 | H15: GWP-L3-270 FS | I15: =IF($G15=0,J14,WORKDAY.INTL(J14,1,11)) -> 46483 | J15: =IF(G15=0,I15,WORKDAY.INTL(I15,G15-1,11)) -> 46493
A16: GWP-L3-280 | B16: GWP.01.10 | C16: L3 | D16: Geotechnical investigation & soil report | E16: Task | F16: PMC / Consultant | G16: 25 | H16: GWP-L3-270 FS | I16: =IF($G16=0,J14,WORKDAY.INTL(J14,1,11)) -> 46483 | J16: =IF(G16=0,I16,WORKDAY.INTL(I16,G16-1,11)) -> 46511
A17: GWP-PH-2 | B17: GWP.02 | C17: Phase | D17: Statutory Clearances & Inspections | G17: =NETWORKDAYS.INTL(I17,J17,11) -> 515 | I17: =MIN(I18:I28) -> 46389 | J17: =MAX(J18:J28) -> 46989
A18: GWP-L3-300 | B18: GWP.02.01 | C18: L3 | D18: Prepare statutory application documents (site details, process description) | E18: Task | F18: PMC / Consultant | G18: 30 | H18: GWP-L3-200 FS | I18: =IF($G18=0,J7,WORKDAY.INTL(J7,1,11)) -> 46389 | J18: =IF(G18=0,I18,WORKDAY.INTL(I18,G18-1,11)) -> 46423
A19: GWP-L3-310 | B19: GWP.02.02 | C19: L3 | D19: Land use / zoning permission (Town Planning) | E19: Task | F19: Company ABC | G19: 45 | H19: GWP-L3-250 FS; GWP-L3-300 FS | I19: =MAX(IF($G19=0,J12,WORKDAY.INTL(J12,1,11)),IF($G19=0,J18,WORKDAY.INTL(J18,1,11))) -> 46459 | J19: =IF(G19=0,I19,WORKDAY.INTL(I19,G19-1,11)) -> 46511
A20: GWP-L3-320 | B20: GWP.02.03 | C20: L3 | D20: Consent to Establish (State Pollution Control Board) | E20: Task | F20: Company ABC | G20: 60 | H20: GWP-L3-310 FS | I20: =IF($G20=0,J19,WORKDAY.INTL(J19,1,11)) -> 46512 | J20: =IF(G20=0,I20,WORKDAY.INTL(I20,G20-1,11)) -> 46581
A21: GWP-L3-330 | B21: GWP.02.04 | C21: L3 | D21: Building plan approval (Town Planning Authority) | E21: Task | F21: Company ABC | G21: 40 | H21: GWP-L3-510 FS | I21: =IF($G21=0,J41,WORKDAY.INTL(J41,1,11)) -> 46529 | J21: =IF(G21=0,I21,WORKDAY.INTL(I21,G21-1,11)) -> 46575
A22: GWP-L3-340 | B22: GWP.02.05 | C22: L3 | D22: Groundwater / borewell NOC | E22: Task | F22: Company ABC | G22: 30 | H22: GWP-L3-310 FS | I22: =IF($G22=0,J19,WORKDAY.INTL(J19,1,11)) -> 46512 | J22: =IF(G22=0,I22,WORKDAY.INTL(I22,G22-1,11)) -> 46546
A23: GWP-L3-350 | B23: GWP.02.06 | C23: L3 | D23: Electrical drawings approval & power sanction (Electrical Inspectorate) | E23: Task | F23: Company ABC | G23: 35 | H23: GWP-L3-550 FS | I23: =IF($G23=0,J45,WORKDAY.INTL(J45,1,11)) -> 46529 | J23: =IF(G23=0,I23,WORKDAY.INTL(I23,G23-1,11)) -> 46569
A24: GWP-L3-360 | B24: GWP.02.07 | C24: L3 | D24: Fire safety provisional NOC | E24: Task | F24: Company ABC | G24: 30 | H24: GWP-L3-330 FS | I24: =IF($G24=0,J21,WORKDAY.INTL(J21,1,11)) -> 46576 | J24: =IF(G24=0,I24,WORKDAY.INTL(I24,G24-1,11)) -> 46610
A25: GWP-L3-370 | B25: GWP.02.08 | C25: L3 | D25: Labour licence & BOCW registration for construction | E25: Task | F25: Contractor | G25: 10 | H25: GWP-L3-630 FS | I25: =IF($G25=0,J54,WORKDAY.INTL(J54,1,11)) -> 46646 | J25: =IF(G25=0,I25,WORKDAY.INTL(I25,G25-1,11)) -> 46657
A26: GWP-L3-380 | B26: GWP.02.09 | C26: L3 | D26: Consent to Operate application & inspection (SPCB) | E26: Task | F26: Company ABC | G26: 30 | H26: GWP-L3-900 FS | I26: =IF($G26=0,J90,WORKDAY.INTL(J90,1,11)) -> 46955 | J26: =IF(G26=0,I26,WORKDAY.INTL(I26,G26-1,11)) -> 46989
A27: GWP-L3-385 | B27: GWP.02.10 | C27: L3 | D27: Electrical Inspector approval for energisation | E27: Task | F27: Company ABC | G27: 25 | H27: GWP-L3-090 FS | I27: =IF($G27=0,J85,WORKDAY.INTL(J85,1,11)) -> 46924 | J27: =IF(G27=0,I27,WORKDAY.INTL(I27,G27-1,11)) -> 46952
A28: GWP-L3-390 | B28: GWP.02.11 | C28: L3 | D28: Final fire safety NOC (inspection) | E28: Task | F28: Company ABC | G28: 25 | H28: GWP-L3-080 FS | I28: =IF($G28=0,J84,WORKDAY.INTL(J84,1,11)) -> 46878 | J28: =IF(G28=0,I28,WORKDAY.INTL(I28,G28-1,11)) -> 46906
A29: GWP-PH-3 | B29: GWP.03 | C29: Phase | D29: Utility Arrangements | G29: =NETWORKDAYS.INTL(I29,J29,11) -> 160 | I29: =MIN(I30:I38) -> 46459 | J29: =MAX(J30:J38) -> 46645
A30: GWP-L3-400 | B30: GWP.03.01 | C30: L3 | D30: Power: load sanction application to DISCOM | E30: Task | F30: Company ABC | G30: 20 | H30: GWP-L3-250 FS | I30: =IF($G30=0,J12,WORKDAY.INTL(J12,1,11)) -> 46459 | J30: =IF(G30=0,I30,WORKDAY.INTL(I30,G30-1,11)) -> 46482
A31: GWP-L3-410 | B31: GWP.03.02 | C31: L3 | D31: Power: DISCOM estimate & payment | E31: Task | F31: Company ABC | G31: 20 | H31: GWP-L3-400 FS | I31: =IF($G31=0,J30,WORKDAY.INTL(J30,1,11)) -> 46483 | J31: =IF(G31=0,I31,WORKDAY.INTL(I31,G31-1,11)) -> 46505
A32: GWP-L3-420 | B32: GWP.03.03 | C32: L3 | D32: Power: 11 kV line, metering & HT connection by DISCOM | E32: Task | F32: DISCOM | G32: 100 | H32: GWP-L3-410 FS | I32: =IF($G32=0,J31,WORKDAY.INTL(J31,1,11)) -> 46506 | J32: =IF(G32=0,I32,WORKDAY.INTL(I32,G32-1,11)) -> 46622
A33: GWP-L3-430 | B33: GWP.03.04 | C33: L3 | D33: Water: source permission from municipal water board | E33: Task | F33: Company ABC | G33: 30 | H33: GWP-L3-250 FS | I33: =IF($G33=0,J12,WORKDAY.INTL(J12,1,11)) -> 46459 | J33: =IF(G33=0,I33,WORKDAY.INTL(I33,G33-1,11)) -> 46493
A34: GWP-L3-440 | B34: GWP.03.05 | C34: L3 | D34: Water: pipeline connection to site | E34: Task | F34: Municipality | G34: 45 | H34: GWP-L3-430 FS | I34: =IF($G34=0,J33,WORKDAY.INTL(J33,1,11)) -> 46494 | J34: =IF(G34=0,I34,WORKDAY.INTL(I34,G34-1,11)) -> 46546
A35: GWP-L3-450 | B35: GWP.03.06 | C35: L3 | D35: Approach road & site access improvement | E35: Task | F35: Municipality | G35: 40 | H35: GWP-L3-270 FS | I35: =IF($G35=0,J14,WORKDAY.INTL(J14,1,11)) -> 46483 | J35: =IF(G35=0,I35,WORKDAY.INTL(I35,G35-1,11)) -> 46528
A36: GWP-L3-460 | B36: GWP.03.07 | C36: L3 | D36: Feedstock supply agreement with municipality (waste quantity, tipping fee) | E36: Task | F36: Company ABC | G36: 60 | H36: GWP-L3-220 FS | I36: =IF($G36=0,J9,WORKDAY.INTL(J9,1,11)) -> 46459 | J36: =IF(G36=0,I36,WORKDAY.INTL(I36,G36-1,11)) -> 46528
A37: GWP-L3-470 | B37: GWP.03.08 | C37: L3 | D37: Treated water / storm discharge point permission | E37: Task | F37: Company ABC | G37: 25 | H37: GWP-L3-310 FS | I37: =IF($G37=0,J19,WORKDAY.INTL(J19,1,11)) -> 46512 | J37: =IF(G37=0,I37,WORKDAY.INTL(I37,G37-1,11)) -> 46540
A38: GWP-L3-480 | B38: GWP.03.09 | C38: L3 | D38: Telecom & internet connectivity for SCADA | E38: Task | F38: Company ABC | G38: 20 | H38: GWP-L3-420 FS | I38: =IF($G38=0,J32,WORKDAY.INTL(J32,1,11)) -> 46623 | J38: =IF(G38=0,I38,WORKDAY.INTL(I38,G38-1,11)) -> 46645
A39: GWP-PH-4 | B39: GWP.04 | C39: Phase | D39: Design & Engineering | G39: =NETWORKDAYS.INTL(I39,J39,11) -> 216 | I39: =MIN(I40:I49) -> 46436 | J39: =MAX(J40:J49) -> 46687
A40: GWP-L3-500 | B40: GWP.04.01 | C40: L3 | D40: Basic engineering: process flow, mass balance & P&IDs | E40: Task | F40: PMC / Consultant | G40: 40 | H40: GWP-L3-210 FS | I40: =IF($G40=0,J8,WORKDAY.INTL(J8,1,11)) -> 46436 | J40: =IF(G40=0,I40,WORKDAY.INTL(I40,G40-1,11)) -> 46482
A41: GWP-L3-510 | B41: GWP.04.02 | C41: L3 | D41: Plot plan & general arrangement of buildings | E41: Task | F41: PMC / Consultant | G41: 30 | H41: GWP-L3-500 FS; GWP-L3-275 FS | I41: =MAX(IF($G41=0,J40,WORKDAY.INTL(J40,1,11)),IF($G41=0,J15,WORKDAY.INTL(J15,1,11))) -> 46494 | J41: =IF(G41=0,I41,WORKDAY.INTL(I41,G41-1,11)) -> 46528
A42: GWP-L3-520 | B42: GWP.04.03 | C42: L3 | D42: Civil & structural design: foundations & RCC (IFC) | E42: Task | F42: PMC / Consultant | G42: 60 | H42: GWP-L3-510 FS; GWP-L3-280 FS | I42: =MAX(IF($G42=0,J41,WORKDAY.INTL(J41,1,11)),IF($G42=0,J16,WORKDAY.INTL(J16,1,11))) -> 46529 | J42: =IF(G42=0,I42,WORKDAY.INTL(I42,G42-1,11)) -> 46598
A43: GWP-L3-530 | B43: GWP.04.04 | C43: L3 | D43: Structural steel design, fabrication drawings & IFC release (incl. shop drawing approval) | E43: Task | F43: PMC / Consultant | G43: 76 | H43: GWP-L3-520 FS | I43: =IF($G43=0,J42,WORKDAY.INTL(J42,1,11)) -> 46599 | J43: =IF(G43=0,I43,WORKDAY.INTL(I43,G43-1,11)) -> 46687
A44: GWP-L3-540 | B44: GWP.04.05 | C44: L3 | D44: Mechanical equipment specifications & datasheets | E44: Task | F44: PMC / Consultant | G44: 25 | H44: GWP-L3-500 FS | I44: =IF($G44=0,J40,WORKDAY.INTL(J40,1,11)) -> 46483 | J44: =IF(G44=0,I44,WORKDAY.INTL(I44,G44-1,11)) -> 46511
A45: GWP-L3-550 | B45: GWP.04.06 | C45: L3 | D45: Electrical design (single line diagram, load list, layouts) | E45: Task | F45: PMC / Consultant | G45: 40 | H45: GWP-L3-500 FS | I45: =IF($G45=0,J40,WORKDAY.INTL(J40,1,11)) -> 46483 | J45: =IF(G45=0,I45,WORKDAY.INTL(I45,G45-1,11)) -> 46528
A46: GWP-L3-560 | B46: GWP.04.07 | C46: L3 | D46: Instrumentation & control design (I/O list, PLC architecture) | E46: Task | F46: PMC / Consultant | G46: 40 | H46: GWP-L3-500 FS | I46: =IF($G46=0,J40,WORKDAY.INTL(J40,1,11)) -> 46483 | J46: =IF(G46=0,I46,WORKDAY.INTL(I46,G46-1,11)) -> 46528
A47: GWP-L3-570 | B47: GWP.04.08 | C47: L3 | D47: Piping, ETP & fire water design and isometrics | E47: Task | F47: PMC / Consultant | G47: 45 | H47: GWP-L3-500 FS; GWP-L3-540 FS | I47: =MAX(IF($G47=0,J40,WORKDAY.INTL(J40,1,11)),IF($G47=0,J44,WORKDAY.INTL(J44,1,11))) -> 46512 | J47: =IF(G47=0,I47,WORKDAY.INTL(I47,G47-1,11)) -> 46563
A48: GWP-L3-580 | B48: GWP.04.09 | C48: L3 | D48: HAZOP / safety review & design freeze | E48: Task | F48: PMC / Consultant | G48: 10 | H48: GWP-L3-570 FS; GWP-L3-550 FS; GWP-L3-560 FS | I48: =MAX(IF($G48=0,J47,WORKDAY.INTL(J47,1,11)),IF($G48=0,J45,WORKDAY.INTL(J45,1,11)),IF($G48=0,J46,WORKDAY.INTL(J46,1,11))) -> 46564 | J48: =IF(G48=0,I48,WORKDAY.INTL(I48,G48-1,11)) -> 46575
A49: GWP-L3-590 | B49: GWP.04.10 | C49: L3 | D49: Vendor drawing review & approval (foundation loads, anchor details) | E49: Task | F49: PMC / Consultant | G49: 40 | H49: GWP-L3-660 FS | I49: =IF($G49=0,J57,WORKDAY.INTL(J57,1,11)) -> 46599 | J49: =IF(G49=0,I49,WORKDAY.INTL(I49,G49-1,11)) -> 46645
A50: GWP-PH-5 | B50: GWP.05 | C50: Phase | D50: Procurement | G50: =NETWORKDAYS.INTL(I50,J50,11) -> 130 | I50: =MIN(I51:I61) -> 46512 | J50: =MAX(J51:J61) -> 46662
A51: GWP-L3-600 | B51: GWP.05.01 | C51: L3 | D51: Tender documents & BOQ for construction contract | E51: Task | F51: PMC / Consultant | G51: 30 | H51: GWP-L3-510 FS | I51: =IF($G51=0,J41,WORKDAY.INTL(J41,1,11)) -> 46529 | J51: =IF(G51=0,I51,WORKDAY.INTL(I51,G51-1,11)) -> 46563
A52: GWP-L3-610 | B52: GWP.05.02 | C52: L3 | D52: Tender floating, pre-bid meeting & bid submission | E52: Task | F52: Company ABC | G52: 35 | H52: GWP-L3-600 FS | I52: =IF($G52=0,J51,WORKDAY.INTL(J51,1,11)) -> 46564 | J52: =IF(G52=0,I52,WORKDAY.INTL(I52,G52-1,11)) -> 46604
A53: GWP-L3-620 | B53: GWP.05.03 | C53: L3 | D53: Technical & commercial evaluation | E53: Task | F53: Company ABC | G53: 20 | H53: GWP-L3-610 FS | I53: =IF($G53=0,J52,WORKDAY.INTL(J52,1,11)) -> 46605 | J53: =IF(G53=0,I53,WORKDAY.INTL(I53,G53-1,11)) -> 46627
A54: GWP-L3-630 | B54: GWP.05.04 | C54: L3 | D54: Negotiation, approval & Letter of Award (LOA) | E54: Task | F54: Company ABC | G54: 15 | H54: GWP-L3-620 FS | I54: =IF($G54=0,J53,WORKDAY.INTL(J53,1,11)) -> 46629 | J54: =IF(G54=0,I54,WORKDAY.INTL(I54,G54-1,11)) -> 46645
A55: GWP-L3-640 | B55: GWP.05.05 | C55: L3 | D55: Contract signing, performance guarantee & mobilisation advance | E55: Task | F55: Company ABC | G55: 15 | H55: GWP-L3-630 FS | I55: =IF($G55=0,J54,WORKDAY.INTL(J54,1,11)) -> 46646 | J55: =IF(G55=0,I55,WORKDAY.INTL(I55,G55-1,11)) -> 46662
A56: GWP-L3-650 | B56: GWP.05.06 | C56: L3 | D56: Process equipment: tender & evaluation (trommel, conveyors, shredder, baler) | E56: Task | F56: Company ABC | G56: 60 | H56: GWP-L3-540 FS | I56: =IF($G56=0,J44,WORKDAY.INTL(J44,1,11)) -> 46512 | J56: =IF(G56=0,I56,WORKDAY.INTL(I56,G56-1,11)) -> 46581
A57: GWP-L3-660 | B57: GWP.05.07 | C57: L3 | D57: Process equipment: negotiation & purchase order | E57: Task | F57: Company ABC | G57: 15 | H57: GWP-L3-650 FS | I57: =IF($G57=0,J56,WORKDAY.INTL(J56,1,11)) -> 46582 | J57: =IF(G57=0,I57,WORKDAY.INTL(I57,G57-1,11)) -> 46598
A58: GWP-L3-670 | B58: GWP.05.08 | C58: L3 | D58: Composting equipment: tender, evaluation & purchase order | E58: Task | F58: Company ABC | G58: 75 | H58: GWP-L3-540 FS | I58: =IF($G58=0,J44,WORKDAY.INTL(J44,1,11)) -> 46512 | J58: =IF(G58=0,I58,WORKDAY.INTL(I58,G58-1,11)) -> 46598
A59: GWP-L3-680 | B59: GWP.05.09 | C59: L3 | D59: ETP skid & pumps: tender, evaluation & purchase order | E59: Task | F59: Company ABC | G59: 75 | H59: GWP-L3-570 FS | I59: =IF($G59=0,J47,WORKDAY.INTL(J47,1,11)) -> 46564 | J59: =IF(G59=0,I59,WORKDAY.INTL(I59,G59-1,11)) -> 46651
A60: GWP-L3-690 | B60: GWP.05.10 | C60: L3 | D60: Electrical equipment (transformer, HT/LT panels, DG): tender, evaluation & PO | E60: Task | F60: Company ABC | G60: 90 | H60: GWP-L3-550 FS | I60: =IF($G60=0,J45,WORKDAY.INTL(J45,1,11)) -> 46529 | J60: =IF(G60=0,I60,WORKDAY.INTL(I60,G60-1,11)) -> 46633
A61: GWP-L3-695 | B61: GWP.05.11 | C61: L3 | D61: PLC/SCADA & instruments: tender, evaluation & PO | E61: Task | F61: Company ABC | G61: 75 | H61: GWP-L3-560 FS | I61: =IF($G61=0,J46,WORKDAY.INTL(J46,1,11)) -> 46529 | J61: =IF(G61=0,I61,WORKDAY.INTL(I61,G61-1,11)) -> 46616
A62: GWP-PH-6 | B62: GWP.06 | C62: Phase | D62: Equipment Manufacture, Inspection & Delivery | G62: =NETWORKDAYS.INTL(I62,J62,11) -> 261 | I62: =MIN(I63:I74) -> 46599 | J62: =MAX(J63:J74) -> 46903
A63: GWP-L3-810 | B63: GWP.06.01 | C63: L3 | D63: Manufacture & factory inspection (FAT): Trommel, conveyors, feed hopper & weighbridge | E63: Task | F63: Supplier | G63: 189 | H63: GWP-L3-660 FS | I63: =IF($G63=0,J57,WORKDAY.INTL(J57,1,11)) -> 46599 | J63: =IF(G63=0,I63,WORKDAY.INTL(I63,G63-1,11)) -> 46819
A64: GWP-L3-815 | B64: GWP.06.02 | C64: L3 | D64: Dispatch & delivery at site: Trommel, conveyors, feed hopper & weighbridge | E64: Task | F64: Supplier | G64: 12 | H64: GWP-L3-810 FS | I64: =IF($G64=0,J63,WORKDAY.INTL(J63,1,11)) -> 46820 | J64: =IF(G64=0,I64,WORKDAY.INTL(I64,G64-1,11)) -> 46833
A65: GWP-L3-820 | B65: GWP.06.03 | C65: L3 | D65: Manufacture & factory inspection (FAT): Shredder & baling press | E65: Task | F65: Supplier | G65: 199 | H65: GWP-L3-660 FS | I65: =IF($G65=0,J57,WORKDAY.INTL(J57,1,11)) -> 46599 | J65: =IF(G65=0,I65,WORKDAY.INTL(I65,G65-1,11)) -> 46830
A66: GWP-L3-825 | B66: GWP.06.04 | C66: L3 | D66: Dispatch & delivery at site: Shredder & baling press | E66: Task | F66: Supplier | G66: 12 | H66: GWP-L3-820 FS | I66: =IF($G66=0,J65,WORKDAY.INTL(J65,1,11)) -> 46832 | J66: =IF(G66=0,I66,WORKDAY.INTL(I66,G66-1,11)) -> 46844
A67: GWP-L3-830 | B67: GWP.06.05 | C67: L3 | D67: Manufacture & factory inspection (FAT): Composting equipment (blowers, turner, screen) | E67: Task | F67: Supplier | G67: 194 | H67: GWP-L3-670 FS | I67: =IF($G67=0,J58,WORKDAY.INTL(J58,1,11)) -> 46599 | J67: =IF(G67=0,I67,WORKDAY.INTL(I67,G67-1,11)) -> 46825
A68: GWP-L3-835 | B68: GWP.06.06 | C68: L3 | D68: Dispatch & delivery at site: Composting equipment (blowers, turner, screen) | E68: Task | F68: Supplier | G68: 12 | H68: GWP-L3-830 FS | I68: =IF($G68=0,J67,WORKDAY.INTL(J67,1,11)) -> 46826 | J68: =IF(G68=0,I68,WORKDAY.INTL(I68,G68-1,11)) -> 46839
A69: GWP-L3-840 | B69: GWP.06.07 | C69: L3 | D69: Manufacture & factory inspection (FAT): ETP skid, leachate & fire water pumps | E69: Task | F69: Supplier | G69: 154 | H69: GWP-L3-680 FS | I69: =IF($G69=0,J59,WORKDAY.INTL(J59,1,11)) -> 46652 | J69: =IF(G69=0,I69,WORKDAY.INTL(I69,G69-1,11)) -> 46830
A70: GWP-L3-845 | B70: GWP.06.08 | C70: L3 | D70: Dispatch & delivery at site: ETP skid, leachate & fire water pumps | E70: Task | F70: Supplier | G70: 12 | H70: GWP-L3-840 FS | I70: =IF($G70=0,J69,WORKDAY.INTL(J69,1,11)) -> 46832 | J70: =IF(G70=0,I70,WORKDAY.INTL(I70,G70-1,11)) -> 46844
A71: GWP-L3-850 | B71: GWP.06.09 | C71: L3 | D71: Manufacture & factory inspection (FAT): Transformer, HT/LT panels & DG set | E71: Task | F71: Supplier | G71: 189 | H71: GWP-L3-690 FS | I71: =IF($G71=0,J60,WORKDAY.INTL(J60,1,11)) -> 46634 | J71: =IF(G71=0,I71,WORKDAY.INTL(I71,G71-1,11)) -> 46854
A72: GWP-L3-855 | B72: GWP.06.10 | C72: L3 | D72: Dispatch & delivery at site: Transformer, HT/LT panels & DG set | E72: Task | F72: Supplier | G72: 12 | H72: GWP-L3-850 FS | I72: =IF($G72=0,J71,WORKDAY.INTL(J71,1,11)) -> 46855 | J72: =IF(G72=0,I72,WORKDAY.INTL(I72,G72-1,11)) -> 46868
A73: GWP-L3-860 | B73: GWP.06.11 | C73: L3 | D73: Manufacture & factory inspection (FAT): PLC/SCADA panels & field instruments | E73: Task | F73: Supplier | G73: 234 | H73: GWP-L3-695 FS | I73: =IF($G73=0,J61,WORKDAY.INTL(J61,1,11)) -> 46617 | J73: =IF(G73=0,I73,WORKDAY.INTL(I73,G73-1,11)) -> 46889
A74: GWP-L3-865 | B74: GWP.06.12 | C74: L3 | D74: Dispatch & delivery at site: PLC/SCADA panels & field instruments | E74: Task | F74: Supplier | G74: 12 | H74: GWP-L3-860 FS | I74: =IF($G74=0,J73,WORKDAY.INTL(J73,1,11)) -> 46890 | J74: =IF(G74=0,I74,WORKDAY.INTL(I74,G74-1,11)) -> 46903
A75: GWP-PH-7 | B75: GWP.07 | C75: Phase | D75: Construction (Contractor Package) | G75: =NETWORKDAYS.INTL(I75,J75,11) -> 250 | I75: =MIN(I76:I88) -> 46664 | J75: =MAX(J76:J88) -> 46954
A76: GWP-L3-000 | B76: GWP.07.01 | C76: L3 | D76: Site handover to construction contractor | E76: Task | F76: Company ABC | G76: 1 | H76: GWP-L3-640 FS; GWP-L3-370 FS; GWP-L3-270 FS; GWP-L3-450 FS; GWP-L3-320 FS; GWP-L3-330 FS | I76: =MAX(IF($G76=0,J55,WORKDAY.INTL(J55,1,11)),IF($G76=0,J25,WORKDAY.INTL(J25,1,11)),IF($G76=0,J14,WORKDAY.INTL(J14,1,11)),IF($G76=0,J35,WORKDAY.INTL(J35,1,11)),IF($G76=0,J20,WORKDAY.INTL(J20,1,11)),IF($G76=0,J21,WORKDAY.INTL(J21,1,11))) -> 46664 | J76: =IF(G76=0,I76,WORKDAY.INTL(I76,G76-1,11)) -> 46664
A77: GWP-L3-010 | B77: GWP.07.02 | C77: L3 | D77: Site Mobilisation & Temporary Facilities | E77: Fixed link | F77: Construction contractor | G77: =NETWORKDAYS.INTL(I77,J77,11) -> 14 | H77: Fixed: taken from L4-L6 Schedule workbook | I77: 46664 | J77: 46679
A78: GWP-L3-020 | B78: GWP.07.03 | C78: L3 | D78: Site Development & Enabling Works | E78: Fixed link | F78: Construction contractor | G78: =NETWORKDAYS.INTL(I78,J78,11) -> 166 | H78: Fixed: taken from L4-L6 Schedule workbook | I78: 46680 | J78: 46872
A79: GWP-L3-030 | B79: GWP.07.04 | C79: L3 | D79: Civil Works - Process Buildings | E79: Fixed link | F79: Construction contractor | G79: =NETWORKDAYS.INTL(I79,J79,11) -> 70 | H79: Fixed: taken from L4-L6 Schedule workbook | I79: 46709 | J79: 46790
A80: GWP-L3-040 | B80: GWP.07.05 | C80: L3 | D80: Civil Works - Composting Yard, RDF Shed & Leachate Tanks | E80: Fixed link | F80: Construction contractor | G80: =NETWORKDAYS.INTL(I80,J80,11) -> 38 | H80: Fixed: taken from L4-L6 Schedule workbook | I80: 46709 | J80: 46752
A81: GWP-L3-050 | B81: GWP.07.06 | C81: L3 | D81: Civil Works - Administration & Utility Buildings | E81: Fixed link | F81: Construction contractor | G81: =NETWORKDAYS.INTL(I81,J81,11) -> 74 | H81: Fixed: taken from L4-L6 Schedule workbook | I81: 46709 | J81: 46794
A82: GWP-L3-060 | B82: GWP.07.07 | C82: L3 | D82: Structural Steel Fabrication & Erection | E82: Fixed link | F82: Construction contractor | G82: =NETWORKDAYS.INTL(I82,J82,11) -> 110 | H82: Fixed: taken from L4-L6 Schedule workbook | I82: 46688 | J82: 46815
A83: GWP-L3-070 | B83: GWP.07.08 | C83: L3 | D83: Mechanical Equipment Erection | E83: Fixed link | F83: Construction contractor | G83: =NETWORKDAYS.INTL(I83,J83,11) -> 22 | H83: Fixed: taken from L4-L6 Schedule workbook | I83: 46834 | J83: 46858
A84: GWP-L3-080 | B84: GWP.07.09 | C84: L3 | D84: Piping, Fire Water & ETP Mechanical Works | E84: Fixed link | F84: Construction contractor | G84: =NETWORKDAYS.INTL(I84,J84,11) -> 163 | H84: Fixed: taken from L4-L6 Schedule workbook | I84: 46688 | J84: 46877
A85: GWP-L3-090 | B85: GWP.07.10 | C85: L3 | D85: Electrical Installation | E85: Fixed link | F85: Construction contractor | G85: =NETWORKDAYS.INTL(I85,J85,11) -> 176 | H85: Fixed: taken from L4-L6 Schedule workbook | I85: 46718 | J85: 46923
A86: GWP-L3-100 | B86: GWP.07.11 | C86: L3 | D86: Instrumentation & Automation Installation | E86: Fixed link | F86: Construction contractor | G86: =NETWORKDAYS.INTL(I86,J86,11) -> 107 | H86: Fixed: taken from L4-L6 Schedule workbook | I86: 46805 | J86: 46928
A87: GWP-L3-110 | B87: GWP.07.12 | C87: L3 | D87: Construction Inspection, Testing & Mechanical Completion | E87: Fixed link | F87: Construction contractor | G87: =NETWORKDAYS.INTL(I87,J87,11) -> 119 | H87: Fixed: taken from L4-L6 Schedule workbook | I87: 46816 | J87: 46954
A88: GWP-L3-120 | B88: GWP.07.13 | C88: L3 | D88: PMC site supervision, quality surveillance & progress monitoring | E88: Task | F88: PMC / Consultant | G88: =NETWORKDAYS.INTL(I88,J88,11) -> 250 | H88: GWP-L3-000 SS; finishes with GWP-L3-110 | I88: =I76 -> 46664 | J88: =J87 -> 46954
A89: GWP-PH-8 | B89: GWP.08 | C89: Phase | D89: Completion, Pre-commissioning & Commissioning | G89: =NETWORKDAYS.INTL(I89,J89,11) -> 135 | I89: =MIN(I90:I97) -> 46953 | J89: =MAX(J90:J97) -> 47109
A90: GWP-L3-900 | B90: GWP.08.01 | C90: L3 | D90: Mechanical Completion of plant (all packages) | E90: Milestone | F90: PMC / Contractor | G90: 0 | H90: GWP-L3-110 FS; GWP-L3-815 FS; GWP-L3-825 FS; GWP-L3-835 FS; GWP-L3-845 FS; GWP-L3-855 FS; GWP-L3-865 FS | I90: =MAX(IF($G90=0,J87,WORKDAY.INTL(J87,1,11)),IF($G90=0,J64,WORKDAY.INTL(J64,1,11)),IF($G90=0,J66,WORKDAY.INTL(J66,1,11)),IF($G90=0,J68,WORKDAY.INTL(J68,1,11)),IF($G90=0,J70,WORKDAY.INTL(J70,1,11)),IF($G90=0,J72,WORKDAY.INTL(J72,1,11)),IF($G90=0,J74,WORKDAY.INTL(J74,1,11))) -> 46954 | J90: =IF(G90=0,I90,WORKDAY.INTL(I90,G90-1,11)) -> 46954
A91: GWP-L3-905 | B91: GWP.08.02 | C91: L3 | D91: Grid power charging & HT energisation | E91: Task | F91: Company ABC | G91: 5 | H91: GWP-L3-385 FS; GWP-L3-420 FS | I91: =MAX(IF($G91=0,J27,WORKDAY.INTL(J27,1,11)),IF($G91=0,J32,WORKDAY.INTL(J32,1,11))) -> 46953 | J91: =IF(G91=0,I91,WORKDAY.INTL(I91,G91-1,11)) -> 46958
A92: GWP-L3-910 | B92: GWP.08.03 | C92: L3 | D92: Pre-commissioning: flushing, cold runs, loop simulation & power-on | E92: Task | F92: Contractor / Suppliers | G92: 30 | H92: GWP-L3-900 FS; GWP-L3-905 FS; GWP-L3-440 FS; GWP-L3-480 FS | I92: =MAX(IF($G92=0,J90,WORKDAY.INTL(J90,1,11)),IF($G92=0,J91,WORKDAY.INTL(J91,1,11)),IF($G92=0,J34,WORKDAY.INTL(J34,1,11)),IF($G92=0,J38,WORKDAY.INTL(J38,1,11))) -> 46959 | J92: =IF(G92=0,I92,WORKDAY.INTL(I92,G92-1,11)) -> 46993
A93: GWP-L3-930 | B93: GWP.08.04 | C93: L3 | D93: Vendor commissioning support & operator training | E93: Task | F93: Suppliers | G93: 25 | H93: GWP-L3-910 SS+10 | I93: =WORKDAY.INTL(I92,10,11) -> 46970 | J93: =IF(G93=0,I93,WORKDAY.INTL(I93,G93-1,11)) -> 46998
A94: GWP-L3-940 | B94: GWP.08.05 | C94: L3 | D94: Hot commissioning: waste feed start-up & stabilisation | E94: Task | F94: Company ABC | G94: 60 | H94: GWP-L3-910 FS; GWP-L3-380 FS; GWP-L3-460 FS; GWP-L3-390 FS | I94: =MAX(IF($G94=0,J92,WORKDAY.INTL(J92,1,11)),IF($G94=0,J26,WORKDAY.INTL(J26,1,11)),IF($G94=0,J36,WORKDAY.INTL(J36,1,11)),IF($G94=0,J28,WORKDAY.INTL(J28,1,11))) -> 46994 | J94: =IF(G94=0,I94,WORKDAY.INTL(I94,G94-1,11)) -> 47063
A95: GWP-L3-950 | B95: GWP.08.06 | C95: L3 | D95: Performance guarantee test run at rated capacity | E95: Task | F95: Company ABC | G95: 40 | H95: GWP-L3-940 FS | I95: =IF($G95=0,J94,WORKDAY.INTL(J94,1,11)) -> 47064 | J95: =IF(G95=0,I95,WORKDAY.INTL(I95,G95-1,11)) -> 47109
A96: GWP-L3-960 | B96: GWP.08.07 | C96: L3 | D96: As-built drawings, O&M manuals & test records dossier | E96: Task | F96: PMC / Consultant | G96: 50 | H96: GWP-L3-940 SS+10 | I96: =WORKDAY.INTL(I94,10,11) -> 47005 | J96: =IF(G96=0,I96,WORKDAY.INTL(I96,G96-1,11)) -> 47063
A97: GWP-L3-970 | B97: GWP.08.08 | C97: L3 | D97: Commissioning acceptance & handover to operations | E97: Milestone | F97: Company ABC | G97: 0 | H97: GWP-L3-950 FS; GWP-L3-960 FS; GWP-L3-930 FS | I97: =MAX(IF($G97=0,J95,WORKDAY.INTL(J95,1,11)),IF($G97=0,J96,WORKDAY.INTL(J96,1,11)),IF($G97=0,J93,WORKDAY.INTL(J93,1,11))) -> 47109 | J97: =IF(G97=0,I97,WORKDAY.INTL(I97,G97-1,11)) -> 47109

Sheet Key Dates
A1: Key Dates and Consistency Checks
A2: All dates are looked up from the L3 Schedule sheet.
A4: Milestone | B4: Activity ID | C4: Date | D4: Basis
A5: Investment approval | B5: GWP-L3-200 | C5: =INDEX('L3 Schedule'!$J$6:$J$97,MATCH(B5,'L3 Schedule'!$A$6:$A$97,0)) -> 46388 | D5: Finish
A6: Land possession achieved | B6: GWP-L3-270 | C6: =INDEX('L3 Schedule'!$J$6:$J$97,MATCH(B6,'L3 Schedule'!$A$6:$A$97,0)) -> 46482 | D6: Finish
A7: Consent to Establish granted | B7: GWP-L3-320 | C7: =INDEX('L3 Schedule'!$J$6:$J$97,MATCH(B7,'L3 Schedule'!$A$6:$A$97,0)) -> 46581 | D7: Finish
A8: Letter of Award to construction contractor | B8: GWP-L3-630 | C8: =INDEX('L3 Schedule'!$J$6:$J$97,MATCH(B8,'L3 Schedule'!$A$6:$A$97,0)) -> 46645 | D8: Finish
A9: Contract signed | B9: GWP-L3-640 | C9: =INDEX('L3 Schedule'!$J$6:$J$97,MATCH(B9,'L3 Schedule'!$A$6:$A$97,0)) -> 46662 | D9: Finish
A10: Site handover to contractor | B10: GWP-L3-000 | C10: =INDEX('L3 Schedule'!$I$6:$I$97,MATCH(B10,'L3 Schedule'!$A$6:$A$97,0)) -> 46664 | D10: Start
A11: Structural steel IFC drawings released | B11: GWP-L3-530 | C11: =INDEX('L3 Schedule'!$J$6:$J$97,MATCH(B11,'L3 Schedule'!$A$6:$A$97,0)) -> 46687 | D11: Finish
A12: Delivery at site: trommel, conveyors, feed hopper, weighbridge | B12: GWP-L3-815 | C12: =INDEX('L3 Schedule'!$J$6:$J$97,MATCH(B12,'L3 Schedule'!$A$6:$A$97,0)) -> 46833 | D12: Finish
A13: Delivery at site: shredder & baling press | B13: GWP-L3-825 | C13: =INDEX('L3 Schedule'!$J$6:$J$97,MATCH(B13,'L3 Schedule'!$A$6:$A$97,0)) -> 46844 | D13: Finish
A14: Delivery at site: composting equipment | B14: GWP-L3-835 | C14: =INDEX('L3 Schedule'!$J$6:$J$97,MATCH(B14,'L3 Schedule'!$A$6:$A$97,0)) -> 46839 | D14: Finish
A15: Delivery at site: ETP skid & pumps | B15: GWP-L3-845 | C15: =INDEX('L3 Schedule'!$J$6:$J$97,MATCH(B15,'L3 Schedule'!$A$6:$A$97,0)) -> 46844 | D15: Finish
A16: Delivery at site: transformer, panels, DG | B16: GWP-L3-855 | C16: =INDEX('L3 Schedule'!$J$6:$J$97,MATCH(B16,'L3 Schedule'!$A$6:$A$97,0)) -> 46868 | D16: Finish
A17: Delivery at site: PLC/SCADA & instruments | B17: GWP-L3-865 | C17: =INDEX('L3 Schedule'!$J$6:$J$97,MATCH(B17,'L3 Schedule'!$A$6:$A$97,0)) -> 46903 | D17: Finish
A18: Mechanical Completion | B18: GWP-L3-900 | C18: =INDEX('L3 Schedule'!$J$6:$J$97,MATCH(B18,'L3 Schedule'!$A$6:$A$97,0)) -> 46954 | D18: Finish
A19: Grid power charged | B19: GWP-L3-905 | C19: =INDEX('L3 Schedule'!$J$6:$J$97,MATCH(B19,'L3 Schedule'!$A$6:$A$97,0)) -> 46958 | D19: Finish
A20: Consent to Operate obtained | B20: GWP-L3-380 | C20: =INDEX('L3 Schedule'!$J$6:$J$97,MATCH(B20,'L3 Schedule'!$A$6:$A$97,0)) -> 46989 | D20: Finish
A21: Pre-commissioning complete | B21: GWP-L3-910 | C21: =INDEX('L3 Schedule'!$J$6:$J$97,MATCH(B21,'L3 Schedule'!$A$6:$A$97,0)) -> 46993 | D21: Finish
A22: Commissioning acceptance & handover | B22: GWP-L3-970 | C22: =INDEX('L3 Schedule'!$J$6:$J$97,MATCH(B22,'L3 Schedule'!$A$6:$A$97,0)) -> 47109 | D22: Finish
A24: Checks
A25: Handover date required by contractor L4-L6 schedule | C25: 46664
A26: Site handover date in this L3 schedule | C26: =C10 -> 46664
A27: Handover check | C27: =IF(C26<=C25,"OK - handover is on or before required date","LATE - contractor schedule cannot start") -> OK - handover is on or before required date
A28: Months from approval to commissioning acceptance | C28: =ROUND((C22-C5)/30.4375,1) -> 23.7
A29: Working days of float to 31-Dec-2028 target | C29: =NETWORKDAYS.INTL(C22,DATE(2028,12,31),11)-1 -> 7
A31: Handover required date is the "Site handover" input of the L4-L6 Schedule workbook (Assumptions sheet). Update both if you change it.
